{
  "types": [
    "CompartmentDefinition"
  ],
  "CompartmentDefinition": {
    "elements": {
      "CompartmentDefinition": {
        "old-min": 1,
        "new-min": 0,
        "old-max": "1",
        "new-max": "*"
      },
      "CompartmentDefinition.version": {
        "status": "new"
      },
      "CompartmentDefinition.experimental": {
        "modifier": "removed"
      },
      "CompartmentDefinition.resource.code": {
        "binding-codes-changed": true,
        "removed-codes": [
          "BodySite",
          "DataElement",
          "DeviceComponent",
          "EligibilityRequest",
          "EligibilityResponse",
          "ExpansionProfile",
          "ImagingManifest",
          "ProcedureRequest",
          "ProcessRequest",
          "ProcessResponse",
          "ReferralRequest",
          "Sequence",
          "ServiceDefinition"
        ],
        "added-codes": [
          "BiologicallyDerivedProduct",
          "BodyStructure",
          "CatalogEntry",
          "ChargeItemDefinition",
          "CoverageEligibilityRequest",
          "CoverageEligibilityResponse",
          "DeviceDefinition",
          "EffectEvidenceSynthesis",
          "EventDefinition",
          "Evidence",
          "EvidenceVariable",
          "ExampleScenario",
          "ImmunizationEvaluation",
          "InsurancePlan",
          "Invoice",
          "ItemInstance",
          "MedicationKnowledge",
          "MedicinalProduct",
          "MedicinalProductAuthorization",
          "MedicinalProductContraindication",
          "MedicinalProductIndication",
          "MedicinalProductIngredient",
          "MedicinalProductInteraction",
          "MedicinalProductManufactured",
          "MedicinalProductPackaged",
          "MedicinalProductPharmaceutical",
          "MedicinalProductUndesirableEffect",
          "MolecularSequence",
          "ObservationDefinition",
          "OrganizationAffiliation",
          "ResearchDefinition",
          "ResearchElementDefinition",
          "RiskEvidenceSynthesis",
          "ServiceRequest",
          "SpecimenDefinition",
          "SubstanceNucleicAcid",
          "SubstancePolymer",
          "SubstanceProtein",
          "SubstanceReferenceInformation",
          "SubstanceSourceMaterial",
          "SubstanceSpecification",
          "TerminologyCapabilities",
          "VerificationResult"
        ],
        "binding-status": "changed",
        "old-binding": {
          "reference": "http://hl7.org/fhir/ValueSet/resource-types",
          "strength": "required"
        },
        "new-binding": {
          "reference": "http://hl7.org/fhir/ValueSet/resource-types",
          "strength": "required"
        }
      },
      "CompartmentDefinition.title": {
        "status": "deleted"
      },
      "CompartmentDefinition.jurisdiction": {
        "status": "deleted"
      }
    },
    "status": "changed"
  }
}